ostruct/__init__.py
ostruct/openstruct.py
ostruct-4.0.1.dist-info/LICENSE
ostruct-4.0.1.dist-info/METADATA
ostruct-4.0.1.dist-info/WHEEL
ostruct-4.0.1.dist-info/top_level.txt
ostruct-4.0.1.dist-info/RECORD
