Metadata-Version: 2.1
Name: ostruct
Version: 4.0.1
Summary: OpenStruct Data Structure
Home-page: http://github.com/hamidnazari/python-ostruct
Author: Hamid Nazari
Author-email: hn@linux.com
License: MIT
Keywords: ostruct,openstruct,data structure,data structures
Classifier: Programming Language :: Python
Classifier: Programming Language :: Python :: 3
Classifier: Programming Language :: Python :: 3.8
Classifier: Programming Language :: Python :: 3.9
Classifier: Programming Language :: Python :: 3.10
Classifier: Programming Language :: Python :: 3.11
Classifier: Programming Language :: Python :: 3.12
Classifier: Intended Audience :: Developers
Classifier: License :: OSI Approved :: MIT License
Classifier: Operating System :: OS Independent
Classifier: Topic :: Software Development
Classifier: Topic :: Software Development :: Libraries
Classifier: Topic :: Software Development :: Libraries :: Python Modules
Classifier: Development Status :: 5 - Production/Stable
License-File: LICENSE
